worksheet_grading/__init__.py
worksheet_grading/config.py
worksheet_grading/grade.py
worksheet_grading/grade_export.py
worksheet_grading/grade_import.py
worksheet_grading/gradelib.py
worksheet_grading/moodle_util.py
worksheet_grading/split.py
worksheet_grading/util.py
worksheet_grading-1.4.4.dist-info/LICENSE
worksheet_grading-1.4.4.dist-info/METADATA
worksheet_grading-1.4.4.dist-info/WHEEL
worksheet_grading-1.4.4.dist-info/entry_points.txt
worksheet_grading-1.4.4.dist-info/top_level.txt
worksheet_grading-1.4.4.dist-info/RECORD
