Metadata-Version: 2.1
Name: worksheet-grading
Version: 1.4.4
Summary: Exercise sheet grading utility with Moodle support
Home-page: https://gitlab.com/kdvkrs/worksheet_grading
Author: Klaus Kraßnitzer
Author-email: klaus@krss.at
Classifier: Programming Language :: Python :: 3
Classifier: License :: OSI Approved :: MIT License
Requires-Python: >=3.7
License-File: LICENSE
Requires-Dist: readchar
Requires-Dist: colorama
Requires-Dist: pandas
